simpilfont/__init__.py
simpilfont/font.py
simpilfont-24.5.18.dist-info/LICENSE
simpilfont-24.5.18.dist-info/METADATA
simpilfont-24.5.18.dist-info/WHEEL
simpilfont-24.5.18.dist-info/top_level.txt
simpilfont-24.5.18.dist-info/RECORD
