Metadata-Version: 2.1
Name: simpilfont
Version: 24.5.18
Summary: A "family size style" request system that simplifies loading remote fonts with PIL
Author-email: Oyster Shucker <onemadgypsy@gmail.com>
Maintainer-email: Oyster Shucker <onemadgypsy@gmail.com>
Project-URL: Homepage, https://github.com/OneMadGypsy/SimPIL-Font/
Project-URL: Issues, https://github.com/OneMadGypsy/SimPIL-Font/issues
Keywords: PIL,Pillow,font,ImageFont
Classifier: Intended Audience :: Developers
Classifier: Development Status :: 4 - Beta
Classifier: License :: OSI Approved :: MIT License
Classifier: Operating System :: OS Independent
Classifier: Programming Language :: Python :: 3
Requires-Python: >=3.8
License-File: LICENSE
Requires-Dist: Pillow
